proptables/__init__.py
proptables/R134a/R134a_PresSat.csv
proptables/R134a/R134a_SupPreSat.csv
proptables/R134a/R134a_Super.csv
proptables/R134a/R134a_TempSat.csv
proptables/water/H2O_Compressed.csv
proptables/water/H2O_PresSat.csv
proptables/water/H2O_Super.csv
proptables/water/H2O_TempSat.csv
proptables/water/H2O_superSat.csv
proptables-0.1.1.dist-info/METADATA
proptables-0.1.1.dist-info/WHEEL
proptables-0.1.1.dist-info/top_level.txt
proptables-0.1.1.dist-info/RECORD
