Metadata-Version: 2.2
Name: proptables
Version: 0.1.1
Summary: For generating property table values for given input
Home-page: https://github.com/Buddhi19/PropertyTables_Python
Author: Buddhi Wijenayake
Author-email: Buddhi Wijenayake <wijenayakebuddhi34802@gmail.com>
License: MIT
Classifier: Programming Language :: Python :: 3
Classifier: License :: OSI Approved :: MIT License
Classifier: Operating System :: OS Independent
Requires-Python: >=3.7
Requires-Dist: numpy>=1.21
Requires-Dist: pandas>=1.3
